anglr.py
anglr-1.1.0.dist-info/top_level.txt
anglr-1.1.0.dist-info/RECORD
anglr-1.1.0.dist-info/metadata.json
anglr-1.1.0.dist-info/DESCRIPTION.rst
anglr-1.1.0.dist-info/WHEEL
anglr-1.1.0.dist-info/pbr.json
anglr-1.1.0.dist-info/METADATA
